LICENSE
MANIFEST.in
README.md
setup.py
categorize/__init__.py
categorize/categories.ini
categorize/config.py
categorize/sorter.py
categorize.egg-info/PKG-INFO
categorize.egg-info/SOURCES.txt
categorize.egg-info/dependency_links.txt
categorize.egg-info/entry_points.txt
categorize.egg-info/top_level.txt