Metadata-Version: 2.1
Name: categorize
Version: 0.1.1
Summary: Categorize is a simple, customizable CLI-tool for automation sorting your files by their extensions.
Home-page: https://github.com/kantegory/categorize
Author: Dobryakov David
Author-email: kantegory@etersoft.ru
License: ISC
Platform: UNKNOWN
Classifier: Development Status :: 4 - Beta
Classifier: Environment :: Plugins
Classifier: Operating System :: POSIX :: Linux
Classifier: Programming Language :: Python :: 3.6
Classifier: Topic :: System
Classifier: Topic :: Utilities
Classifier: Development Status :: 3 - Alpha
